biearce_time/__init__.py
biearce_time/core.py
biearce_time-0.1.0.dist-info/METADATA
biearce_time-0.1.0.dist-info/WHEEL
biearce_time-0.1.0.dist-info/top_level.txt
biearce_time-0.1.0.dist-info/RECORD
