Metadata-Version: 2.4
Name: biearce_time
Version: 0.1.0
Summary: A package that provides a static 'today' timestamp and time functions based on it.
Home-page: https://github.com/yourusername/biearce_time
Author: Your Name
Author-email: Your Name <your.email@example.com>
License-Expression: MIT
Classifier: Programming Language :: Python :: 3
Classifier: Operating System :: OS Independent
Requires-Python: >=3.6
Dynamic: author
Dynamic: home-page
Dynamic: requires-python
